protenc/__init__.py
protenc/console/__init__.py
protenc/console/extract.py
protenc/encoder.py
protenc/io.py
protenc/models.py
protenc/types.py
protenc/utils.py
protenc-0.1.6.dist-info/LICENSE
protenc-0.1.6.dist-info/METADATA
protenc-0.1.6.dist-info/WHEEL
protenc-0.1.6.dist-info/entry_points.txt
protenc-0.1.6.dist-info/RECORD
