Metadata-Version: 2.1
Name: protenc
Version: 0.1.6
Summary: Extract protein embeddings from protein language models.
Home-page: https://github.com/kklemon/ProtEnc
Author: Kristian Klemon
Author-email: kristian.klemon@gmail.com
Requires-Python: >=3.10,<3.13
Classifier: Programming Language :: Python :: 3
Classifier: Programming Language :: Python :: 3.10
Classifier: Programming Language :: Python :: 3.11
Requires-Dist: biopython (>=1.81,<2.0)
Requires-Dist: humanfriendly (>=10.0,<11.0)
Requires-Dist: json-stream (>=2.3.2,<3.0.0)
Requires-Dist: lmdb (>=1.4.1,<2.0.0)
Requires-Dist: pandas (>=2.1.1,<3.0.0)
Requires-Dist: pytest (>=7.4.2,<8.0.0)
Requires-Dist: sentencepiece (>=0.1.99,<0.2.0)
Requires-Dist: tensordict (>=0.1.2,<0.2.0)
Requires-Dist: torch (>=2.0.1,<3.0.0)
Requires-Dist: tqdm (>=4.66.1,<5.0.0)
Requires-Dist: transformers (>=4.33.3,<5.0.0)
Project-URL: Repository, https://github.com/kklemon/ProtEnc
